LICENSE
MANIFEST.in
README.md
setup.cfg
setup.py
mkdocs_multiversion_plugin/__init__.py
mkdocs_multiversion_plugin/entry.py
mkdocs_multiversion_plugin/git.py
mkdocs_multiversion_plugin.egg-info/PKG-INFO
mkdocs_multiversion_plugin.egg-info/SOURCES.txt
mkdocs_multiversion_plugin.egg-info/dependency_links.txt
mkdocs_multiversion_plugin.egg-info/entry_points.txt
mkdocs_multiversion_plugin.egg-info/requires.txt
mkdocs_multiversion_plugin.egg-info/top_level.txt
mkdocs_multiversion_plugin/providers/php.tpl
mkdocs_multiversion_plugin/themes/__init__.py
mkdocs_multiversion_plugin/themes/mkdocs/__init__.py
mkdocs_multiversion_plugin/themes/mkdocs/css/multiversion.css
mkdocs_multiversion_plugin/themes/mkdocs/js/multiversion.js
mkdocs_multiversion_plugin/themes/readthedocs/__init__.py
mkdocs_multiversion_plugin/themes/readthedocs/css/multiversion.css
mkdocs_multiversion_plugin/themes/readthedocs/js/multiversion.js