Metadata-Version: 2.1
Name: mkdocs-multiversion-plugin
Version: 0.2.0
Summary: A plugin that allows you to have several versions of the documentation built with mkdocs
Home-page: https://github.com/blatio/mkdocs-multiversion-plugin
Author: blatio
Author-email: blatio@gmail.com
License: BSD
Project-URL: Bug Tracker, https://github.com/blatio/mkdocs-multiversion-plugin/issues
Classifier: Development Status :: 4 - Beta
Classifier: Intended Audience :: Developers
Classifier: Intended Audience :: Information Technology
Classifier: License :: OSI Approved :: BSD License
Classifier: Programming Language :: Python
Classifier: Programming Language :: Python :: 3.7
Classifier: Programming Language :: Python :: 3.8
Classifier: Programming Language :: Python :: 3.9
Requires-Python: >=3.7
License-File: LICENSE
